narodmon/__init__.py
narodmon/__main__.py
narodmon/interface_api.py
narodmon/interface_json.py
narodmon/narodmon.py
narodmon/settings.py
narodmon/tools.py
narodmon_python_api-0.0.3.dist-info/METADATA
narodmon_python_api-0.0.3.dist-info/WHEEL
narodmon_python_api-0.0.3.dist-info/top_level.txt
narodmon_python_api-0.0.3.dist-info/RECORD
