Metadata-Version: 2.1
Name: narodmon-python-api
Version: 0.0.3
Summary: Narodmon python API
Home-page: https://github.com/wwakabobik/narodmon
Author: Ilya Vereshchagin
Author-email: i.vereshchagin@gmail.com
License: UNKNOWN
Platform: UNKNOWN
Classifier: Programming Language :: Python :: 3
Classifier: License :: OSI Approved :: MIT License
Classifier: Operating System :: OS Independent
Requires-Python: >=3.7
Requires-Dist: requests
